server.py
azure_mcp_agent-0.1.0.dist-info/METADATA
azure_mcp_agent-0.1.0.dist-info/WHEEL
azure_mcp_agent-0.1.0.dist-info/entry_points.txt
azure_mcp_agent-0.1.0.dist-info/top_level.txt
azure_mcp_agent-0.1.0.dist-info/RECORD
