Metadata-Version: 2.4
Name: azure-mcp-agent
Version: 0.1.0
Summary: A Claude MCP server for Azure tasks.
Author-email: Hassen <hvsssen7@gmail.com>
License: MIT
Requires-Python: >=3.10
Requires-Dist: fastapi
Requires-Dist: uvicorn[standard]
Requires-Dist: pydantic
Requires-Dist: mcp
